metroem/__init__.py
metroem/aligner.py
metroem/alignment.py
metroem/augmentations.py
metroem/benchmark.py
metroem/blockmatch.py
metroem/dataset.py
metroem/download_field.py
metroem/download_image.py
metroem/finetuner.py
metroem/helpers.py
metroem/loss.py
metroem/masks.py
metroem/train.py
metroem-0.1.3.dist-info/LICENSE
metroem-0.1.3.dist-info/METADATA
metroem-0.1.3.dist-info/WHEEL
metroem-0.1.3.dist-info/entry_points.txt
metroem-0.1.3.dist-info/top_level.txt
metroem-0.1.3.dist-info/RECORD
