Metadata-Version: 2.1
Name: metroem
Version: 0.1.3
Summary: Metric learning optimization pyramid for EM alignment
Home-page: UNKNOWN
Author: Seung Lab
Author-email: 
License: UNKNOWN
Platform: UNKNOWN
Requires-Python: >=3.7
Requires-Dist: torch
Requires-Dist: torchvision
Requires-Dist: pathlib
Requires-Dist: artificery
Requires-Dist: torchfields
Requires-Dist: h5py
Requires-Dist: argparse
Requires-Dist: cloud-volume
Requires-Dist: tqdm
Requires-Dist: scikit-image
Requires-Dist: six
Requires-Dist: numpy
